hetzner_snap_and_rotate/__init__.py
hetzner_snap_and_rotate/__main__.py
hetzner_snap_and_rotate/__version__.py
hetzner_snap_and_rotate/api.py
hetzner_snap_and_rotate/config.py
hetzner_snap_and_rotate/logger.py
hetzner_snap_and_rotate/periods.py
hetzner_snap_and_rotate/servers.py
hetzner_snap_and_rotate/snapshots.py
hetzner_snap_and_rotate-1.2.6.dist-info/METADATA
hetzner_snap_and_rotate-1.2.6.dist-info/WHEEL
hetzner_snap_and_rotate-1.2.6.dist-info/licenses/LICENSE
hetzner_snap_and_rotate-1.2.6.dist-info/RECORD
