Metadata-Version: 2.3
Name: hetzner_snap_and_rotate
Version: 1.2.6
Summary: Creates and rotates snapshots of Hetzner cloud servers
Project-URL: Homepage, https://github.com/undecaf/hetzner-snap-and-rotate
Project-URL: Issues, https://github.com/undecaf/hetzner-snap-and-rotate/issues
Author-email: "F. Kasper" <fkasper@modus-operandi.at>
Keywords: Backup rotation,Cloud,Hetzner,Snapshot rotation
Classifier: License :: OSI Approved :: MIT License
Classifier: Operating System :: OS Independent
Classifier: Programming Language :: Python :: 3
Requires-Python: >=3.10
Requires-Dist: dataclass-wizard~=0.22.3
Requires-Dist: requests~=2.32.3
Requires-Dist: typing-extensions~=4.13.2
Provides-Extra: tests
Requires-Dist: parameterized~=0.9.0; extra == 'tests'
Requires-Dist: pytest~=8.2.2; extra == 'tests'
Requires-Dist: requests-mock~=1.12.1; extra == 'tests'
Requires-Dist: setuptools~=70.0.0; extra == 'tests'
